crystals/__init__.py
crystals/__main__.py
crystals/affine.py
crystals/atom.py
crystals/atom_data.py
crystals/base.py
crystals/biological.py
crystals/crystal.py
crystals/lattice.py
crystals/parsers.py
crystals/spg_data.py
crystals/writers.py
crystals/cifs/Ac.cif
crystals/cifs/Ag.cif
crystals/cifs/Al.cif
crystals/cifs/Am.cif
crystals/cifs/As.cif
crystals/cifs/Au.cif
crystals/cifs/B.cif
crystals/cifs/Ba.cif
crystals/cifs/BaTiO3_cubic.cif
crystals/cifs/Be.cif
crystals/cifs/Bi.cif
crystals/cifs/Br.cif
crystals/cifs/C.cif
crystals/cifs/Ca.cif
crystals/cifs/Cd.cif
crystals/cifs/Ce-gamma.cif
crystals/cifs/Co.cif
crystals/cifs/Cr.cif
crystals/cifs/Cs.cif
crystals/cifs/Cu.cif
crystals/cifs/Dy.cif
crystals/cifs/Er.cif
crystals/cifs/Eu.cif
crystals/cifs/Fe.cif
crystals/cifs/FeAs.cif
crystals/cifs/Ga.cif
crystals/cifs/GaAs.cif
crystals/cifs/Gd.cif
crystals/cifs/Ge.cif
crystals/cifs/Hf.cif
crystals/cifs/Ho.cif
crystals/cifs/I.cif
crystals/cifs/In.cif
crystals/cifs/Ir.cif
crystals/cifs/K.cif
crystals/cifs/La.cif
crystals/cifs/Li.cif
crystals/cifs/Lu.cif
crystals/cifs/Mg.cif
crystals/cifs/Mn.cif
crystals/cifs/Mo.cif
crystals/cifs/Na.cif
crystals/cifs/Nb.cif
crystals/cifs/Nd.cif
crystals/cifs/Ni.cif
crystals/cifs/Np.cif
crystals/cifs/Os.cif
crystals/cifs/P.cif
crystals/cifs/Pb.cif
crystals/cifs/Pd.cif
crystals/cifs/Pr.cif
crystals/cifs/Pt.cif
crystals/cifs/Pu-alpha.cif
crystals/cifs/Pu-delta.cif
crystals/cifs/Pu-epsilon.cif
crystals/cifs/Pu-gamma.cif
crystals/cifs/Rb.cif
crystals/cifs/Re.cif
crystals/cifs/Rh.cif
crystals/cifs/Ru.cif
crystals/cifs/S.cif
crystals/cifs/Sb.cif
crystals/cifs/Sc.cif
crystals/cifs/Si.cif
crystals/cifs/SiC.cif
crystals/cifs/Sm.cif
crystals/cifs/Sn-alpha.cif
crystals/cifs/Sn-beta.cif
crystals/cifs/Sr.cif
crystals/cifs/Ta.cif
crystals/cifs/Tb.cif
crystals/cifs/Th.cif
crystals/cifs/Ti.cif
crystals/cifs/Tl.cif
crystals/cifs/Tm.cif
crystals/cifs/U.cif
crystals/cifs/V.cif
crystals/cifs/W.cif
crystals/cifs/Y.cif
crystals/cifs/Yb.cif
crystals/cifs/Zn.cif
crystals-1.7.0.dist-info/LICENSE
crystals-1.7.0.dist-info/METADATA
crystals-1.7.0.dist-info/WHEEL
crystals-1.7.0.dist-info/entry_points.txt
crystals-1.7.0.dist-info/top_level.txt
crystals-1.7.0.dist-info/RECORD
