Metadata-Version: 2.1
Name: crystals
Version: 1.7.0
Summary: Data structures for crystallography
Home-page: http://crystals.readthedocs.io
Author: Laurent P. René de Cotret
Author-email: laurent.decotret@outlook.com
Maintainer: Laurent P. René de Cotret
Maintainer-email: laurent.decotret@outlook.com
License: GPLv3
Download-URL: http://github.com/LaurentRDC/crystals
Project-URL: Documentation, https://crystals.readthedocs.io/
Project-URL: Source, https://github.com/LaurentRDC/crystals
Keywords: crystallography,material science,structural biology
Platform: UNKNOWN
Classifier: Environment :: Console
Classifier: Development Status :: 5 - Production/Stable
Classifier: Intended Audience :: Developers
Classifier: Intended Audience :: Education
Classifier: Intended Audience :: Science/Research
Classifier: License :: OSI Approved :: GNU General Public License v3 (GPLv3)
Classifier: Natural Language :: English
Classifier: Operating System :: OS Independent
Classifier: Programming Language :: Python
Classifier: Programming Language :: Python :: 3
Classifier: Topic :: Scientific/Engineering
Classifier: Topic :: Scientific/Engineering :: Chemistry
Classifier: Topic :: Scientific/Engineering :: Physics
Classifier: Topic :: Scientific/Engineering :: Bio-Informatics
Requires-Python: >=3.7
License-File: LICENSE
Requires-Dist: numpy<3,>=1.20
Requires-Dist: spglib<3,>=1.15
Requires-Dist: pycifrw<5,>=4.4.1
Requires-Dist: requests<3,>=2
